conferencemapper/__init__.py
conferencemapper/app.py
conferencemapper-1.0.1.dist-info/licenses/LICENSE
conferencemapper-1.0.1.dist-info/METADATA
conferencemapper-1.0.1.dist-info/WHEEL
conferencemapper-1.0.1.dist-info/top_level.txt
conferencemapper-1.0.1.dist-info/RECORD
