Metadata-Version: 2.4
Name: conferencemapper
Version: 1.0.1
Summary: Jigasi ConferenceMapper with Redis, Flask and Gunicorn
Author-email: Christoph Settgast <csett86_git@quicksands.de>
License-Expression: Apache-2.0
Project-URL: Homepage, https://github.com/luki-ev/conferencemapper
Project-URL: Bug Tracker, https://github.com/luki-ev/conferencemapper/issues
Classifier: Programming Language :: Python :: 3
Classifier: Operating System :: OS Independent
Requires-Python: >=3.9
License-File: LICENSE
Requires-Dist: redis
Requires-Dist: flask
Provides-Extra: test
Requires-Dist: pytest>=7.0.0; extra == "test"
Requires-Dist: fakeredis>=2.0.0; extra == "test"
Dynamic: license-file
